mycalc/calculator.py
Sejin-0.0.1.dist-info/METADATA
Sejin-0.0.1.dist-info/WHEEL
Sejin-0.0.1.dist-info/top_level.txt
Sejin-0.0.1.dist-info/RECORD
