Metadata-Version: 2.1
Name: Sejin
Version: 0.0.1
Summary: oss-dev my calculator 0001
Home-page: https://github.com/Jelly1500/calc0001
Download-URL: https://github.com/Jelly1500/calc0001/archive/refs/tags/v0.0.1.zip
Author: Heosejin
License: UNKNOWN
Platform: UNKNOWN
Classifier: Programming Language :: Python :: 3
